magnet2torrent/__init__.py
magnet2torrent/__main__.py
magnet2torrent/bencode.py
magnet2torrent/exceptions.py
magnet2torrent/httptracker.py
magnet2torrent/magnet2torrent.py
magnet2torrent/peer.py
magnet2torrent/server.py
magnet2torrent/settings.py
magnet2torrent/udptracker.py
magnet2torrent/dht/__init__.py
magnet2torrent/dht/crawling.py
magnet2torrent/dht/network.py
magnet2torrent/dht/node.py
magnet2torrent/dht/protocol.py
magnet2torrent/dht/routing.py
magnet2torrent/dht/storage.py
magnet2torrent/dht/utils.py
magnet2torrent-1.2.1.dist-info/LICENSE.md
magnet2torrent-1.2.1.dist-info/METADATA
magnet2torrent-1.2.1.dist-info/WHEEL
magnet2torrent-1.2.1.dist-info/entry_points.txt
magnet2torrent-1.2.1.dist-info/top_level.txt
magnet2torrent-1.2.1.dist-info/RECORD
