Metadata-Version: 2.1
Name: magnet2torrent
Version: 1.2.1
Summary: Turn a bittorrent magnet links into a .torrent file.
Home-page: https://github.com/JohnDoee/magnet2torrent
Author: Anders Jensen
Author-email: andersandjensen@gmail.com
License: MIT
Classifier: Development Status :: 4 - Beta
Classifier: Environment :: Web Environment
Classifier: Intended Audience :: End Users/Desktop
Classifier: License :: OSI Approved :: MIT License
Classifier: Operating System :: OS Independent
Classifier: Programming Language :: Python
Classifier: Programming Language :: Python :: 3.8
Classifier: Programming Language :: Python :: 3.9
Classifier: Programming Language :: Python :: 3.10
Classifier: Programming Language :: Python :: 3.11
Classifier: Programming Language :: Python :: 3.12
Classifier: Topic :: Internet :: WWW/HTTP
License-File: LICENSE.md
Requires-Dist: aiohttp ==3.*
Requires-Dist: expiringdict >=1.2.0
